{
  "_hinweis": "Automatisch erzeugt vom Bierradar-Scraper. Quelle: marktguru.de. Nicht von Hand bearbeiten.",
  "stand": "2026-05-31T13:19:09.236172+02:00",
  "quelle": "marktguru.de",
  "fehler": [],
  "angebote": [
    {
      "bier_id": "veltins",
      "bier_name": "Veltins",
      "markt_name": "Combi",
      "markt_ort": "Breuna",
      "titel": "HINWEIS: MIT MOIN CARD 13.99 € 20 x 0,33-l-Kiste zzgl. 3.10 Pfand",
      "preis": "14,99",
      "gueltig_bis": null,
      "gebinde_typ": "Kasten",
      "anzahl": 20,
      "einzelgroesse_l": 0.33,
      "gesamt_l": 6.6,
      "preis_pro_liter": "2,27",
      "quelle": "marktguru"
    },
    {
      "bier_id": "veltins",
      "bier_name": "Veltins",
      "markt_name": "Netto Marken-Discount",
      "markt_ort": "Breuna",
      "titel": "18 x 0,33 l zzgl. Pfand 4.50",
      "preis": "9,99",
      "gueltig_bis": null,
      "gebinde_typ": "Kasten",
      "anzahl": 18,
      "einzelgroesse_l": 0.33,
      "gesamt_l": 5.94,
      "preis_pro_liter": "1,68",
      "quelle": "marktguru"
    },
    {
      "bier_id": "veltins",
      "bier_name": "Veltins",
      "markt_name": "Combi",
      "markt_ort": "Breuna",
      "titel": "20 x 0,33-l-Kiste zzgl. 3.10 Pfand",
      "preis": "9,99",
      "gueltig_bis": null,
      "gebinde_typ": "Kasten",
      "anzahl": 20,
      "einzelgroesse_l": 0.33,
      "gesamt_l": 6.6,
      "preis_pro_liter": "1,51",
      "quelle": "marktguru"
    }
  ]
}